{
  "artworks": [
    {
      "title": "Berglandschap in Tirol met gemzen Rijksmuseum SK-A-4927",
      "artist": "Dutch Master",
      "year": "1858",
      "image_url": "https://commons.wikimedia.org/wiki/Special:FilePath/Berglandschap_in_Tirol_met_gemzen_Rijksmuseum_SK-A-4927.jpeg?width=1920",
      "gallery": "landscape",
      "source": "rijks"
    },
    {
      "title": "Heuvellandschap bij Wageningen Rijksmuseum SK-A-4924",
      "artist": "Dutch Master",
      "year": "1838",
      "image_url": "https://commons.wikimedia.org/wiki/Special:FilePath/Heuvellandschap_bij_Wageningen_Rijksmuseum_SK-A-4924.jpeg?width=1920",
      "gallery": "landscape",
      "source": "rijks"
    },
    {
      "title": "Het onweer Rijksmuseum SK-A-4926",
      "artist": "Dutch Master",
      "year": "1843",
      "image_url": "https://commons.wikimedia.org/wiki/Special:FilePath/Het_onweer_Rijksmuseum_SK-A-4926.jpeg?width=1920",
      "gallery": "landscape",
      "source": "rijks"
    },
    {
      "title": "George Hendrik Breitner - Gezicht op het Oosterpark te Amsterdam in de sneeuw",
      "artist": "Dutch Master",
      "year": "1892",
      "image_url": "https://commons.wikimedia.org/wiki/Special:FilePath/George_Hendrik_Breitner_-_Gezicht_op_het_Oosterpark_te_Amsterdam_in_de_sneeuw.jpg?width=1920",
      "gallery": "landscape",
      "source": "rijks"
    },
    {
      "title": "Francesco Guardi - De brand in de wijk van San Marcuola",
      "artist": "Dutch Master",
      "year": "1500",
      "image_url": "https://commons.wikimedia.org/wiki/Special:FilePath/Francesco_Guardi_-_De_brand_in_de_wijk_van_San_Marcuola.jpg?width=1920",
      "gallery": "landscape",
      "source": "rijks"
    },
    {
      "title": "Bartholomeus Spranger - Venus en Adonis - SK-A-3888 - Rijksmuseum",
      "artist": "Dutch Master",
      "year": "1587",
      "image_url": "https://commons.wikimedia.org/wiki/Special:FilePath/Bartholomeus_Spranger_-_Venus_en_Adonis_-_SK-A-3888_-_Rijksmuseum.jpg?width=1920",
      "gallery": "landscape",
      "source": "rijks"
    },
    {
      "title": "Aelbert Cuyp - Landschap met koeien en herdersjongen",
      "artist": "Dutch Master",
      "year": "1650",
      "image_url": "https://commons.wikimedia.org/wiki/Special:FilePath/Aelbert_Cuyp_-_Landschap_met_koeien_en_herdersjongen.jpg?width=1920",
      "gallery": "landscape",
      "source": "rijks"
    },
    {
      "title": "Abraham Bloemaert - Landschap met groenten en vruchten op de voorgrond",
      "artist": "Dutch Master",
      "year": "1657",
      "image_url": "https://commons.wikimedia.org/wiki/Special:FilePath/Abraham_Bloemaert_-_Landschap_met_groenten_en_vruchten_op_de_voorgrond.jpg?width=1920",
      "gallery": "landscape",
      "source": "rijks"
    },
    {
      "title": "Gerrit van Santen - Het beleg van Schenckenschans door prins Frederik Hendrik, april 1636",
      "artist": "Dutch Master",
      "year": "1650",
      "image_url": "https://commons.wikimedia.org/wiki/Special:FilePath/Gerrit_van_Santen_-_Het_beleg_van_Schenckenschans_door_prins_Frederik_Hendrik%2C_april_1636.jpg?width=1920",
      "gallery": "landscape",
      "source": "rijks"
    },
    {
      "title": "Zomer Rijksmuseum SK-A-3945",
      "artist": "Dutch Master",
      "year": "1625",
      "image_url": "https://commons.wikimedia.org/wiki/Special:FilePath/Zomer_Rijksmuseum_SK-A-3945.jpeg?width=1920",
      "gallery": "landscape",
      "source": "rijks"
    },
    {
      "title": "Canaletto - De ingang van het Canal Grande bij de Punta della Dogana en de Santa Maria della Salute",
      "artist": "Dutch Master",
      "year": "1730",
      "image_url": "https://commons.wikimedia.org/wiki/Special:FilePath/Canaletto_-_De_ingang_van_het_Canal_Grande_bij_de_Punta_della_Dogana_en_de_Santa_Maria_della_Salute.jpg?width=1920",
      "gallery": "landscape",
      "source": "rijks"
    },
    {
      "title": "Caneletto - Het Canal Grande met de Ponte Rialto en de Fondaco dei Tedeschi",
      "artist": "Dutch Master",
      "year": "1730",
      "image_url": "https://commons.wikimedia.org/wiki/Special:FilePath/Caneletto_-_Het_Canal_Grande_met_de_Ponte_Rialto_en_de_Fondaco_dei_Tedeschi.jpg?width=1920",
      "gallery": "landscape",
      "source": "rijks"
    },
    {
      "title": "Lodewijk XIV trekt bij Lobith Nederland binnen Rijksmuseum SK-A-3753",
      "artist": "Dutch Master",
      "year": "1690",
      "image_url": "https://commons.wikimedia.org/wiki/Special:FilePath/Lodewijk_XIV_trekt_bij_Lobith_Nederland_binnen_Rijksmuseum_SK-A-3753.jpeg?width=1920",
      "gallery": "landscape",
      "source": "rijks"
    },
    {
      "title": "Francesco Guardi - Regatta op het Canal Grande bij de Rialtobrug te Venetië",
      "artist": "Dutch Master",
      "year": "1780",
      "image_url": "https://commons.wikimedia.org/wiki/Special:FilePath/Francesco_Guardi_-_Regatta_op_het_Canal_Grande_bij_de_Rialtobrug_te_Veneti%C3%AB.jpg?width=1920",
      "gallery": "landscape",
      "source": "rijks"
    },
    {
      "title": "Gezicht op de Nieuwe Gracht bij het Bolwerk te Haarlem Rijksmuseum SK-A-3943",
      "artist": "Dutch Master",
      "year": "1815",
      "image_url": "https://commons.wikimedia.org/wiki/Special:FilePath/Gezicht_op_de_Nieuwe_Gracht_bij_het_Bolwerk_te_Haarlem_Rijksmuseum_SK-A-3943.jpeg?width=1920",
      "gallery": "landscape",
      "source": "rijks"
    },
    {
      "title": "Duinlandschap Rijksmuseum SK-A-3847",
      "artist": "Dutch Master",
      "year": "1855",
      "image_url": "https://commons.wikimedia.org/wiki/Special:FilePath/Duinlandschap_Rijksmuseum_SK-A-3847.jpeg?width=1920",
      "gallery": "landscape",
      "source": "rijks"
    },
    {
      "title": "The View from the Batavian Embassy in Paris, Josephus Augustus Knip, 1801",
      "artist": "Dutch Master",
      "year": "1801",
      "image_url": "https://commons.wikimedia.org/wiki/Special:FilePath/The_View_from_the_Batavian_Embassy_in_Paris%2C_Josephus_Augustus_Knip%2C_1801.jpg?width=1920",
      "gallery": "landscape",
      "source": "rijks"
    },
    {
      "title": "Wybrand Hendriks - Gezicht op de Nieuwe Gracht bij het Bolwerk te Haarlem - BR2093 - Rijksmuseum Twenthe",
      "artist": "Dutch Master",
      "year": "1815",
      "image_url": "https://commons.wikimedia.org/wiki/Special:FilePath/Wybrand_Hendriks_-_Gezicht_op_de_Nieuwe_Gracht_bij_het_Bolwerk_te_Haarlem_-_BR2093_-_Rijksmuseum_Twenthe.jpg?width=1920",
      "gallery": "landscape",
      "source": "rijks"
    },
    {
      "title": "Riviergezicht met een waltoren geïnspireerd op de Camperveerse toren te Veere Rijksmuseum SK-A-3850",
      "artist": "Dutch Master",
      "year": "1855",
      "image_url": "https://commons.wikimedia.org/wiki/Special:FilePath/Riviergezicht_met_een_waltoren_ge%C3%AFnspireerd_op_de_Camperveerse_toren_te_Veere_Rijksmuseum_SK-A-3850.jpeg?width=1920",
      "gallery": "landscape",
      "source": "rijks"
    },
    {
      "title": "Souvenir du Rhin by Johannes Franciscus Hoppenbrouwers Rijksdienst voor het Cultureel Erfgoed B2255",
      "artist": "Dutch Master",
      "year": "1853",
      "image_url": "https://commons.wikimedia.org/wiki/Special:FilePath/Souvenir_du_Rhin_by_Johannes_Franciscus_Hoppenbrouwers_Rijksdienst_voor_het_Cultureel_Erfgoed_B2255.jpg?width=1920",
      "gallery": "landscape",
      "source": "rijks"
    },
    {
      "title": "Winter op het IJ voor Amsterdam Rijksmuseum SK-A-3922",
      "artist": "Dutch Master",
      "year": "1850",
      "image_url": "https://commons.wikimedia.org/wiki/Special:FilePath/Winter_op_het_IJ_voor_Amsterdam_Rijksmuseum_SK-A-3922.jpeg?width=1920",
      "gallery": "landscape",
      "source": "rijks"
    },
    {
      "title": "Watermolen in een bosachtig landschap Rijksmuseum SK-A-3844",
      "artist": "Dutch Master",
      "year": "1854",
      "image_url": "https://commons.wikimedia.org/wiki/Special:FilePath/Watermolen_in_een_bosachtig_landschap_Rijksmuseum_SK-A-3844.jpeg?width=1920",
      "gallery": "landscape",
      "source": "rijks"
    },
    {
      "title": "Winter Landscape by Johannes Franciscus Hoppenbrouwers Rijksdienst voor het Cultureel Erfgoed B264",
      "artist": "Dutch Master",
      "year": "1865",
      "image_url": "https://commons.wikimedia.org/wiki/Special:FilePath/Winter_Landscape_by_Johannes_Franciscus_Hoppenbrouwers_Rijksdienst_voor_het_Cultureel_Erfgoed_B264.jpg?width=1920",
      "gallery": "landscape",
      "source": "rijks"
    },
    {
      "title": "Adriaen van Ostade 041",
      "artist": "Dutch Master",
      "year": "1650",
      "image_url": "https://commons.wikimedia.org/wiki/Special:FilePath/Adriaen_van_Ostade_041.jpg?width=1920",
      "gallery": "landscape",
      "source": "rijks"
    },
    {
      "title": "Bartholomäus Breenbergh (Groenewegen, P. A.) (1599-1659) - Landschaft mit Ruinen und Staffage - 2053 - Führermuseum",
      "artist": "Dutch Master",
      "year": "1650",
      "image_url": "https://commons.wikimedia.org/wiki/Special:FilePath/Bartholom%C3%A4us_Breenbergh_(Groenewegen%2C_P._A.)_(1599-1659)_-_Landschaft_mit_Ruinen_und_Staffage_-_2053_-_F%C3%BChrermuseum.jpg?width=1920",
      "gallery": "landscape",
      "source": "rijks"
    },
    {
      "title": "Bergachtig landschap met visser Rijksmuseum SK-A-4218",
      "artist": "Dutch Master",
      "year": "1650",
      "image_url": "https://commons.wikimedia.org/wiki/Special:FilePath/Bergachtig_landschap_met_visser_Rijksmuseum_SK-A-4218.jpeg?width=1920",
      "gallery": "landscape",
      "source": "rijks"
    },
    {
      "title": "Boslandschap met rivier Rijksmuseum SK-A-4873",
      "artist": "Dutch Master",
      "year": "1650",
      "image_url": "https://commons.wikimedia.org/wiki/Special:FilePath/Boslandschap_met_rivier_Rijksmuseum_SK-A-4873.jpeg?width=1920",
      "gallery": "landscape",
      "source": "rijks"
    },
    {
      "title": "Gezicht op Ambon Rijksmuseum SK-A-4482",
      "artist": "Dutch Master",
      "year": "1617",
      "image_url": "https://commons.wikimedia.org/wiki/Special:FilePath/Gezicht_op_Ambon_Rijksmuseum_SK-A-4482.jpeg?width=1920",
      "gallery": "landscape",
      "source": "rijks"
    },
    {
      "title": "Italianiserend landschap met een oudtestamentisch onderwerp Rijksmuseum SK-A-4825",
      "artist": "Dutch Master",
      "year": "1620",
      "image_url": "https://commons.wikimedia.org/wiki/Special:FilePath/Italianiserend_landschap_met_een_oudtestamentisch_onderwerp_Rijksmuseum_SK-A-4825.jpeg?width=1920",
      "gallery": "landscape",
      "source": "rijks"
    },
    {
      "title": "Landschap met de bekering van Saul Rijksmuseum SK-A-4919",
      "artist": "Dutch Master",
      "year": "1612",
      "image_url": "https://commons.wikimedia.org/wiki/Special:FilePath/Landschap_met_de_bekering_van_Saul_Rijksmuseum_SK-A-4919.jpeg?width=1920",
      "gallery": "landscape",
      "source": "rijks"
    },
    {
      "title": "Landschap met Tobias en de Engel Rijksmuseum SK-A-4872",
      "artist": "Dutch Master",
      "year": "1620",
      "image_url": "https://commons.wikimedia.org/wiki/Special:FilePath/Landschap_met_Tobias_en_de_Engel_Rijksmuseum_SK-A-4872.jpeg?width=1920",
      "gallery": "landscape",
      "source": "rijks"
    },
    {
      "title": "Jacob van Geel 001",
      "artist": "Dutch Master",
      "year": "1633",
      "image_url": "https://commons.wikimedia.org/wiki/Special:FilePath/Jacob_van_Geel_001.jpg?width=1920",
      "gallery": "landscape",
      "source": "rijks"
    },
    {
      "title": "Braziliaans dorp Rijksmuseum SK-A-4272",
      "artist": "Dutch Master",
      "year": "1677",
      "image_url": "https://commons.wikimedia.org/wiki/Special:FilePath/Braziliaans_dorp_Rijksmuseum_SK-A-4272.jpeg?width=1920",
      "gallery": "landscape",
      "source": "rijks"
    },
    {
      "title": "Landschap met de doop van de Kamerling Rijksmuseum SK-A-4713",
      "artist": "Dutch Master",
      "year": "1630",
      "image_url": "https://commons.wikimedia.org/wiki/Special:FilePath/Landschap_met_de_doop_van_de_Kamerling_Rijksmuseum_SK-A-4713.jpeg?width=1920",
      "gallery": "landscape",
      "source": "rijks"
    },
    {
      "title": "Gezicht op een gefantaseerde stad aan een rivier met de toren van Saint Pol uit Vianen Rijksmuseum SK-A-4879",
      "artist": "Dutch Master",
      "year": "1649",
      "image_url": "https://commons.wikimedia.org/wiki/Special:FilePath/Gezicht_op_een_gefantaseerde_stad_aan_een_rivier_met_de_toren_van_Saint_Pol_uit_Vianen_Rijksmuseum_SK-A-4879.jpeg?width=1920",
      "gallery": "landscape",
      "source": "rijks"
    },
    {
      "title": "De Engels-Nederlandse vloot onder Lord Exmouth en vice-admiraal Jonkheer Theodorus Frederik van Capellen stelt de Algerijnse fortificaties buiten gevecht, 27 augustus 1816. Rijksmuseum SK-A-1380",
      "artist": "Dutch Master",
      "year": "1818",
      "image_url": "https://commons.wikimedia.org/wiki/Special:FilePath/De_Engels-Nederlandse_vloot_onder_Lord_Exmouth_en_vice-admiraal_Jonkheer_Theodorus_Frederik_van_Capellen_stelt_de_Algerijnse_fortificaties_buiten_gevecht%2C_27_augustus_1816._Rijksmuseum_SK-A-1380.jpeg?width=1920",
      "gallery": "landscape",
      "source": "rijks"
    },
    {
      "title": "De Engels-Nederlandse vloot in de Baai van Algiers ter ondersteuning van het ultimatum tot vrijlating van blanke slaven, 26 augustus 1816. Rijksmuseum SK-A-1377",
      "artist": "Dutch Master",
      "year": "1818",
      "image_url": "https://commons.wikimedia.org/wiki/Special:FilePath/De_Engels-Nederlandse_vloot_in_de_Baai_van_Algiers_ter_ondersteuning_van_het_ultimatum_tot_vrijlating_van_blanke_slaven%2C_26_augustus_1816._Rijksmuseum_SK-A-1377.jpeg?width=1920",
      "gallery": "landscape",
      "source": "rijks"
    },
    {
      "title": "Nachtelijk gevecht tussen Cornelis Tromp op de 'Gouden Leeuw' en Sir Edward Spragg op de 'Royal Prince' tijdens de zeeslag bij Kijkduin, 21 augustus 1673; episode uit de Derde Engelse Rijksmuseum SK-A-2393",
      "artist": "Dutch Master",
      "year": "1675",
      "image_url": "https://commons.wikimedia.org/wiki/Special:FilePath/Nachtelijk_gevecht_tussen_Cornelis_Tromp_op_de_'Gouden_Leeuw'_en_Sir_Edward_Spragg_op_de_'Royal_Prince'_tijdens_de_zeeslag_bij_Kijkduin%2C_21_augustus_1673%3B_episode_uit_de_Derde_Engelse_Rijksmuseum_SK-A-2393.jpeg?width=1920",
      "gallery": "landscape",
      "source": "rijks"
    },
    {
      "title": "Battle of Gibraltar 1607",
      "artist": "Dutch Master",
      "year": "1621",
      "image_url": "https://commons.wikimedia.org/wiki/Special:FilePath/Battle_of_Gibraltar_1607.jpg?width=1920",
      "gallery": "landscape",
      "source": "rijks"
    },
    {
      "title": "Een opperkoopman van de VOC, vermoedelijk Jacob Mathieusen en zijn vrouw ; op de achtergrond de retourvloot op de rede van Batavia Rijksmuseum SK-A-2350",
      "artist": "Dutch Master",
      "year": "1650",
      "image_url": "https://commons.wikimedia.org/wiki/Special:FilePath/Een_opperkoopman_van_de_VOC%2C_vermoedelijk_Jacob_Mathieusen_en_zijn_vrouw_%3B_op_de_achtergrond_de_retourvloot_op_de_rede_van_Batavia_Rijksmuseum_SK-A-2350.jpeg?width=1920",
      "gallery": "landscape",
      "source": "rijks"
    },
    {
      "title": "'s Lands oorlogsschip 'Amsterdam' voor de Westerlaag op het IJ voor Amsterdam. Rijksmuseum SK-A-1005",
      "artist": "Dutch Master",
      "year": "1807",
      "image_url": "https://commons.wikimedia.org/wiki/Special:FilePath/'s_Lands_oorlogsschip_'Amsterdam'_voor_de_Westerlaag_op_het_IJ_voor_Amsterdam._Rijksmuseum_SK-A-1005.jpeg?width=1920",
      "gallery": "landscape",
      "source": "rijks"
    },
    {
      "title": "Vroom Hendrick Cornelisz Dutch Ships Ramming Spanish Galleys off the Flemish Coast in October 1602",
      "artist": "Dutch Master",
      "year": "1617",
      "image_url": "https://commons.wikimedia.org/wiki/Special:FilePath/Vroom_Hendrick_Cornelisz_Dutch_Ships_Ramming_Spanish_Galleys_off_the_Flemish_Coast_in_October_1602.jpg?width=1920",
      "gallery": "landscape",
      "source": "rijks"
    },
    {
      "title": "De slag op het Slaak tussen de Nederlandse en Spaanse vloten in de nacht van 12 op 13 september 1631 Rijksmuseum SK-A-454",
      "artist": "Dutch Master",
      "year": "1633",
      "image_url": "https://commons.wikimedia.org/wiki/Special:FilePath/De_slag_op_het_Slaak_tussen_de_Nederlandse_en_Spaanse_vloten_in_de_nacht_van_12_op_13_september_1631_Rijksmuseum_SK-A-454.jpeg?width=1920",
      "gallery": "landscape",
      "source": "rijks"
    },
    {
      "title": "Slag op de Zuiderzee, 6 oktober 1573 (Abraham de Verwer, 1621)",
      "artist": "Dutch Master",
      "year": "1621",
      "image_url": "https://commons.wikimedia.org/wiki/Special:FilePath/Slag_op_de_Zuiderzee%2C_6_oktober_1573_(Abraham_de_Verwer%2C_1621).jpg?width=1920",
      "gallery": "landscape",
      "source": "rijks"
    },
    {
      "title": "De aankomst van koning Karel II van Engeland te Rotterdam, 24 mei 1660, SK-A-448",
      "artist": "Dutch Master",
      "year": "1660",
      "image_url": "https://commons.wikimedia.org/wiki/Special:FilePath/De_aankomst_van_koning_Karel_II_van_Engeland_te_Rotterdam%2C_24_mei_1660%2C_SK-A-448.jpg?width=1920",
      "gallery": "landscape",
      "source": "rijks"
    },
    {
      "title": "Jan van de Cappelle 001",
      "artist": "Dutch Master",
      "year": "1650",
      "image_url": "https://commons.wikimedia.org/wiki/Special:FilePath/Jan_van_de_Cappelle_001.jpg?width=1920",
      "gallery": "landscape",
      "source": "rijks"
    },
    {
      "title": "Vroom Hendrick Cornelisz Battle of Haarlemmermeer",
      "artist": "Dutch Master",
      "year": "1629",
      "image_url": "https://commons.wikimedia.org/wiki/Special:FilePath/Vroom_Hendrick_Cornelisz_Battle_of_Haarlemmermeer.jpg?width=1920",
      "gallery": "landscape",
      "source": "rijks"
    },
    {
      "title": "De verovering van de Royal Prince Rijksmuseum SK-A-438",
      "artist": "Dutch Master",
      "year": "1670",
      "image_url": "https://commons.wikimedia.org/wiki/Special:FilePath/De_verovering_van_de_Royal_Prince_Rijksmuseum_SK-A-438.jpeg?width=1920",
      "gallery": "landscape",
      "source": "rijks"
    },
    {
      "title": "Jan van Goyen 001",
      "artist": "Dutch Master",
      "year": "1660",
      "image_url": "https://commons.wikimedia.org/wiki/Special:FilePath/Jan_van_Goyen_001.jpg?width=1920",
      "gallery": "landscape",
      "source": "rijks"
    },
    {
      "title": "Jeronymus van Diest - Gezicht op Dordrecht - 1453 - Amsterdam Museum",
      "artist": "Dutch Master",
      "year": "1660",
      "image_url": "https://commons.wikimedia.org/wiki/Special:FilePath/Jeronymus_van_Diest_-_Gezicht_op_Dordrecht_-_1453_-_Amsterdam_Museum.jpg?width=1920",
      "gallery": "landscape",
      "source": "rijks"
    },
    {
      "title": "Het verbranden van de Engelse vloot voor Chatham, 20 juni 1667 Rijksmuseum SK-A-307",
      "artist": "Dutch Master",
      "year": "1670",
      "image_url": "https://commons.wikimedia.org/wiki/Special:FilePath/Het_verbranden_van_de_Engelse_vloot_voor_Chatham%2C_20_juni_1667_Rijksmuseum_SK-A-307.jpeg?width=1920",
      "gallery": "landscape",
      "source": "rijks"
    },
    {
      "title": "Het kielhalen van de scheepschirurgijn van admiraal Jan van Nes Rijksmuseum SK-A-449",
      "artist": "Dutch Master",
      "year": "1673",
      "image_url": "https://commons.wikimedia.org/wiki/Special:FilePath/Het_kielhalen_van_de_scheepschirurgijn_van_admiraal_Jan_van_Nes_Rijksmuseum_SK-A-449.jpeg?width=1920",
      "gallery": "landscape",
      "source": "rijks"
    },
    {
      "title": "Havengezicht Rijksmuseum SK-A-437",
      "artist": "Dutch Master",
      "year": "1678",
      "image_url": "https://commons.wikimedia.org/wiki/Special:FilePath/Havengezicht_Rijksmuseum_SK-A-437.jpeg?width=1920",
      "gallery": "landscape",
      "source": "rijks"
    },
    {
      "title": "Slag bij Livorno Rijksmuseum SK-A-294",
      "artist": "Dutch Master",
      "year": "1658",
      "image_url": "https://commons.wikimedia.org/wiki/Special:FilePath/Slag_bij_Livorno_Rijksmuseum_SK-A-294.jpeg?width=1920",
      "gallery": "landscape",
      "source": "rijks"
    },
    {
      "title": "Schepen voor de kust Rijksmuseum SK-A-440",
      "artist": "Dutch Master",
      "year": "1660",
      "image_url": "https://commons.wikimedia.org/wiki/Special:FilePath/Schepen_voor_de_kust_Rijksmuseum_SK-A-440.jpeg?width=1920",
      "gallery": "landscape",
      "source": "rijks"
    }
  ]
}